<?xml version="1.0" encoding="UTF-8"?>
<configuration>

  <property>
    <name>hashing.max.freq</name>
    <value>1000</value>
    <description>Max frequency of a feature in each document to allow adding it to the hashed document.</description>
  </property> 

  <property>
    <name>hashing.binary.weights</name>
    <value>false</value>
    <description>true = ignore features frequencies and assume they all occured once in a document (ie. all have same wight within each document)</description>
  </property>

  <property>
    <name>hashing.lonely.features</name>
    <value>true</value>
    <description>true = hash features appearing in only one document across the corpse (but keep its weight effect on that document).</description>
  </property>

  <property>
    <name>hashing.md5.hash</name>
    <value>false</value>
    <description>true = md5 hash features instead of serial numbering</description>
  </property>

  <property>
    <name>hashing.df.cut</name>
    <value>0.0</value>
    <description>fraction removed from popular features after sorting by popularity in HashMapper.java (eg.0.05 is top 5% popular features) [Elsayed ACL'08].</description>
  </property>

  <property>
    <name>hashing.num.reducers</name>
    <value>5</value>
    <description>Default number of reducers in the job to hash vectors.</description>
  </property>

  <property>    
    <name>hashing.option.num</name>
    <value>3</value>
    <description>Options: (1)collect features (2) featureVectors (3) featureWeightVectors (5) bag of hashed words.DEFAULT:3</description>
  </property> 

</configuration>
